dalib/__init__.py
dalib/adaptation/__init__.py
dalib/adaptation/_util.py
dalib/adaptation/cdan.py
dalib/adaptation/dan.py
dalib/adaptation/dann.py
dalib/adaptation/jan.py
dalib/adaptation/mcd.py
dalib/adaptation/mdd.py
dalib/modules/__init__.py
dalib/modules/classifier.py
dalib/modules/domain_discriminator.py
dalib/modules/grl.py
dalib/modules/kernels.py
dalib/vision/__init__.py
dalib/vision/datasets/__init__.py
dalib/vision/datasets/_util.py
dalib/vision/datasets/domainnet.py
dalib/vision/datasets/imagelist.py
dalib/vision/datasets/office31.py
dalib/vision/datasets/officecaltech.py
dalib/vision/datasets/officehome.py
dalib/vision/datasets/visda2017.py
dalib/vision/models/__init__.py
dalib/vision/models/resnet.py
dalib-0.2.dist-info/LICENSE
dalib-0.2.dist-info/LICENSE.md
dalib-0.2.dist-info/METADATA
dalib-0.2.dist-info/WHEEL
dalib-0.2.dist-info/top_level.txt
dalib-0.2.dist-info/RECORD
