Metadata-Version: 2.1
Name: dalib
Version: 0.2
Summary: A Library for Deep Domain Adaptation
Home-page: https://github.com/thuml/Domain-Adaptation-Lib
Author: THUML
Author-email: JiangJunguang1123@outlook.com
License: UNKNOWN
Keywords: domain adaptation,transfer learning,deep learning,pytorch
Platform: UNKNOWN
Classifier: Development Status :: 3 - Alpha
Classifier: Intended Audience :: Science/Research
Classifier: Topic :: Scientific/Engineering :: Artificial Intelligence
Classifier: Topic :: Software Development :: Libraries :: Python Modules
Classifier: License :: OSI Approved :: MIT License
Classifier: Programming Language :: Python :: 3.6
Classifier: Programming Language :: Python :: 3.7
Classifier: Programming Language :: Python :: 3.8
Requires-Python: >=3.6
Requires-Dist: torch (>=1.4.0)
Requires-Dist: torchvision (>=0.5.0)
Requires-Dist: numpy
Requires-Dist: qpsolvers (>=1.4.0)
Provides-Extra: dev
Requires-Dist: Sphinx ; extra == 'dev'
Requires-Dist: sphinx-rtd-theme ; extra == 'dev'
